LinkToFabricHelper/CdmSchema.py
LinkToFabricHelper/__init__.py
LinkToFabricHelper-0.1.0.dist-info/LICENSE
LinkToFabricHelper-0.1.0.dist-info/METADATA
LinkToFabricHelper-0.1.0.dist-info/WHEEL
LinkToFabricHelper-0.1.0.dist-info/top_level.txt
LinkToFabricHelper-0.1.0.dist-info/RECORD
