Metadata-Version: 2.1
Name: LinkToFabricHelper
Version: 0.1.0
Summary: A small package to help developers make exported data from dataverse via Link to Microsoft Fabric functionality easieer accessible.
Author-email: Martin Hofbauer <martin.hofbauer@hofdatsol.at>
Project-URL: Homepage, https://github.com/MartinHofpower/LinkToFabricHelper
Project-URL: Issues, https://github.com/MartinHofpower/LinkToFabricHelper/issues
Classifier: Programming Language :: Python :: 3
Classifier: License :: OSI Approved :: MIT License
Classifier: Operating System :: OS Independent
Requires-Python: >=3.8
License-File: LICENSE
